{
  "signedContributors": [
    {
      "name": "eric-intuitem",
      "id": 71850047,
      "comment_id": 1937879200,
      "created_at": "2024-02-11T21:38:57Z",
      "repoId": 694266896,
      "pullRequestNo": 34
    },
    {
      "name": "nas-tabchiche",
      "id": 71079376,
      "comment_id": 1938501228,
      "created_at": "2024-02-12T11:30:24Z",
      "repoId": 694266896,
      "pullRequestNo": 36
    },
    {
      "name": "Mohamed-Hacene",
      "id": 90701924,
      "comment_id": 1938587819,
      "created_at": "2024-02-12T12:28:16Z",
      "repoId": 694266896,
      "pullRequestNo": 37
    },
    {
      "name": "Alexdev8",
      "id": 47476131,
      "comment_id": 1943789781,
      "created_at": "2024-02-14T13:39:42Z",
      "repoId": 694266896,
      "pullRequestNo": 49
    },
    {
      "name": "monsieurswag",
      "id": 143810744,
      "comment_id": 1956391957,
      "created_at": "2024-02-21T10:55:25Z",
      "repoId": 694266896,
      "pullRequestNo": 62
    },
    {
      "name": "felixhaeberle",
      "id": 34959078,
      "comment_id": 2018114042,
      "created_at": "2024-03-25T14:19:50Z",
      "repoId": 694266896,
      "pullRequestNo": 173
    },
    {
      "name": "ab-smith",
      "id": 11318384,
      "comment_id": 2028279270,
      "created_at": "2024-03-30T16:56:16Z",
      "repoId": 694266896,
      "pullRequestNo": 184
    },
    {
      "name": "eltociear",
      "id": 22633385,
      "comment_id": 2059572148,
      "created_at": "2024-04-16T17:17:51Z",
      "repoId": 694266896,
      "pullRequestNo": 269
    },
    {
      "name": "protocolpaladin",
      "id": 141778818,
      "comment_id": 2089158171,
      "created_at": "2024-05-01T21:20:07Z",
      "repoId": 694266896,
      "pullRequestNo": 350
    },
    {
      "name": "krismas",
      "id": 1462821,
      "comment_id": 2096090467,
      "created_at": "2024-05-06T14:01:28Z",
      "repoId": 694266896,
      "pullRequestNo": 379
    },
    {
      "name": "tovam",
      "id": 8293335,
      "comment_id": 2120824956,
      "created_at": "2024-05-20T16:49:40Z",
      "repoId": 694266896,
      "pullRequestNo": 463
    }
  ]
}